eqone.py
eqone-0.0.6.dist-info/METADATA
eqone-0.0.6.dist-info/WHEEL
eqone-0.0.6.dist-info/entry_points.txt
eqone-0.0.6.dist-info/top_level.txt
eqone-0.0.6.dist-info/RECORD
