Metadata-Version: 2.1
Name: eqone
Version: 0.0.6
Summary: A package for visualizing worlf earthquske for one month
Home-page: https://github.com/Junya-Toyokura/world-earthquake-one-month
Author: junya toyokura
Author-email: j.toyokura@agreement.jp
License: UNKNOWN
Project-URL: Bug Tracker, https://github.com/Junya-Toyokura/world-earthquake-one-month
Platform: UNKNOWN
Classifier: Programming Language :: Python :: 3
Classifier: License :: OSI Approved :: MIT License
Classifier: Operating System :: OS Independent
Requires-Python: >=3.7
